{"videos": {}, "tags": ["Ladybug", "LBExampleFiles", "Sun path"], "components": {"Ladybug_Gradient Library": 1, "Move": 1, "Ladybug_Open EPW And STAT Weather Files": 1, "Series": 1, "Ladybug_Outdoor Solar Temperature Adjustor": 1, "Extend Curve": 1, "Ladybug_Legend Parameters": 1, "Ladybug_Ladybug": 1, "Ladybug_Outdoor Comfort Calculator": 1, "Unit Z": 1, "Ladybug_Analysis Period": 1, "Ladybug_Day_Month_Hour": 1, "Number Slider": 2, "Brep": 1, "Brep Wireframe": 1, "Ladybug_SunPath": 1, "Ladybug_Import epw": 1, "Text Tag": 1}, "thumbnail": "thumbnail.png", "file": "Map_Annual_Comfort_on_Sunpath.zip", "images": [{"Map_Annual_Comfort_on_Sunpath_GH.png": "Grasshopper Definition"}, {"Map_Annual_Comfort_on_Sunpath_Rhino.png": "Rhino Viewport Screenshot"}], "dependencies": ["Ladybug"]}